setup.py
remy/__init__.py
remy/cli.py
remy/cookbooks.py
remy/github.py
remy/jenkins.py
remy/roles.py
remy.egg-info/PKG-INFO
remy.egg-info/SOURCES.txt
remy.egg-info/dependency_links.txt
remy.egg-info/entry_points.txt
remy.egg-info/requires.txt
remy.egg-info/top_level.txt
remy.egg-info/zip-safe