Metadata-Version: 1.1
Name: remy
Version: 0.1.0
Summary: UNKNOWN
Home-page: https://github.com/gmr/remy
Author: Gavin M. Roy
Author-email: gavinmroy@gmail.com
License: Copyright (c) 2013 Gavin M. Roy
